yummy_cereal/__init__.py
yummy_cereal/exceptions.py
yummy_cereal/protocols.py
yummy_cereal/parsers/__init__.py
yummy_cereal/parsers/annotations_parser.py
yummy_cereal/parsers/validated_parser.py
yummy_cereal/serializers/__init__.py
yummy_cereal/serializers/annotations_serializer.py
yummy_cereal/serializers/validated_serializer.py
yummy_cereal/utils/__init__.py
yummy_cereal/utils/annotations.py
yummy_cereal/utils/formatters.py
yummy_cereal-2.0.3.dist-info/LICENSE.md
yummy_cereal-2.0.3.dist-info/METADATA
yummy_cereal-2.0.3.dist-info/WHEEL
yummy_cereal-2.0.3.dist-info/top_level.txt
yummy_cereal-2.0.3.dist-info/RECORD
