Metadata-Version: 2.1
Name: yummy-cereal
Version: 2.0.3
Summary: Object parser and serializer factories to simplify object configurations
Home-page: https://github.com/JoelLefkowitz/yummy-cereal
Author: Joel Lefkowitz
Author-email: joellefkowitz@hotmail.com
License: UNKNOWN
Keywords: parser,serializer
Platform: UNKNOWN
Classifier: License :: OSI Approved :: MIT License
Classifier: Programming Language :: Python :: 3.7
Classifier: Programming Language :: Python :: 3.8
Requires-Python: >=3.7
Requires-Dist: dataclasses
Requires-Dist: ruamel.yaml
Requires-Dist: typing-extensions
Requires-Dist: typing-inspect
Provides-Extra: dist
Requires-Dist: wheel ; extra == 'dist'
Requires-Dist: twine ; extra == 'dist'
Requires-Dist: bump2version ; extra == 'dist'
Provides-Extra: docs
Requires-Dist: sphinx ; extra == 'docs'
Requires-Dist: pyimport ; extra == 'docs'
Requires-Dist: pypandoc ; extra == 'docs'
Requires-Dist: sphinxcontrib.apidoc ; extra == 'docs'
Requires-Dist: sphinxcontrib.pandoc-markdown ; extra == 'docs'
Requires-Dist: sphinx-autodoc-annotation ; extra == 'docs'
Requires-Dist: yummy-sphinx-theme ; extra == 'docs'
Provides-Extra: tests
Requires-Dist: pytest ; extra == 'tests'
Requires-Dist: pytest-cov ; extra == 'tests'
Requires-Dist: pytest-html ; extra == 'tests'
Requires-Dist: pytest-sugar ; extra == 'tests'
Requires-Dist: pytest-bdd ; extra == 'tests'
Requires-Dist: pytest-watch ; extra == 'tests'
